setup.py
django_db/__init__.py
django_db/settings.py
django_db.egg-info/PKG-INFO
django_db.egg-info/SOURCES.txt
django_db.egg-info/dependency_links.txt
django_db.egg-info/requires.txt
django_db.egg-info/top_level.txt