Metadata-Version: 1.0
Name: django_db
Version: 0.0.7
Summary: A simple way to use django orm not in a classic django project
Home-page: https://github.com/jdxin0/django_db
Author: jdxin0
Author-email: jdxin00@gmail.com
License: MIT
Keywords: django orm db
Platform: UNKNOWN
